YuanmengXiangmuBijiWangzhuanJuejinShicaoXiangmuDianzishu1806/README.md
YuanmengXiangmuBijiWangzhuanJuejinShicaoXiangmuDianzishu1806/__init__.py
YuanmengXiangmuBijiWangzhuanJuejinShicaoXiangmuDianzishu1806/__main__.py
YuanmengXiangmuBijiWangzhuanJuejinShicaoXiangmuDianzishu1806/file.pdf
YuanmengXiangmuBijiWangzhuanJuejinShicaoXiangmuDianzishu1806/index.html
yuanmeng_xiangmu_biji_wangzhuan_juejin_shicao_xiangmu_dianzishu_1806-2024.3.5.0.dist-info/METADATA
yuanmeng_xiangmu_biji_wangzhuan_juejin_shicao_xiangmu_dianzishu_1806-2024.3.5.0.dist-info/WHEEL
yuanmeng_xiangmu_biji_wangzhuan_juejin_shicao_xiangmu_dianzishu_1806-2024.3.5.0.dist-info/entry_points.txt
yuanmeng_xiangmu_biji_wangzhuan_juejin_shicao_xiangmu_dianzishu_1806-2024.3.5.0.dist-info/top_level.txt
yuanmeng_xiangmu_biji_wangzhuan_juejin_shicao_xiangmu_dianzishu_1806-2024.3.5.0.dist-info/RECORD
